scrappier/__init__.py
scrappier/browser.py
scrappier/element.py
scrappier/element_collection.py
scrappier/element_finder.py
scrappier/exceptions/__init__.py
scrappier/exceptions/element_not_found_exception.py
scrappier-1.6.0.dist-info/LICENSE
scrappier-1.6.0.dist-info/METADATA
scrappier-1.6.0.dist-info/WHEEL
scrappier-1.6.0.dist-info/top_level.txt
scrappier-1.6.0.dist-info/RECORD
