Metadata-Version: 2.1
Name: scrappier
Version: 1.6.0
Summary: Scrapper for chrome
Home-page: UNKNOWN
Author: Cristian Guzmán
Author-email: <cristian.guzman.contacto@gmail.com>
License: UNKNOWN
Keywords: python,scrapper,web,scrapping,selenium,scrappier,browser,chrome
Platform: UNKNOWN
License-File: LICENSE
Requires-Dist: pycollection
Requires-Dist: selenium
Requires-Dist: typing
